CHANGELOG.rst
DESCRIPTION.rst
LICENCE
MANIFEST.in
README.rst
setup.py
rabaDB/Raba.py
rabaDB/__init__.py
rabaDB/fields.py
rabaDB/filters.py
rabaDB/rabaSetup.py
rabaDB.egg-info/PKG-INFO
rabaDB.egg-info/SOURCES.txt
rabaDB.egg-info/dependency_links.txt
rabaDB.egg-info/entry_points.txt
rabaDB.egg-info/top_level.txt
rabaDB/examples/BasicExample.py
rabaDB/examples/QueryExample.py
rabaDB/examples/__init__.py