Metadata-Version: 1.1
Name: rabaDB
Version: 1.0.5
Summary: Store, Search, Modify your objects easily. You're welcome.
Home-page: https://github.com/tariqdaouda/rabaDB
Author: Tariq Daouda
Author-email: tariq.daouda@umontreal.ca
License: ApacheV2.0
Keywords: NoSQL database ORM sqlite3
Platform: UNKNOWN
Classifier: Development Status :: 5 - Production/Stable
Classifier: Intended Audience :: Science/Research
Classifier: Intended Audience :: Developers
Classifier: Intended Audience :: System Administrators
Classifier: Topic :: Scientific/Engineering :: Bio-Informatics
Classifier: Topic :: Software Development :: Libraries
Classifier: Topic :: Database
Classifier: Topic :: Database :: Database Engines/Servers
Classifier: Topic :: Database :: Front-Ends
Classifier: License :: OSI Approved :: Apache Software License
Classifier: Programming Language :: Python :: 2.7
